lita/__init__.py
lita/lita.py
lita/model.py
lita/perf.py
lita/utils.py
lita/benchmark/__init__.py
lita/benchmark/commons.py
lita/benchmark/mmlu.py
lita-0.0.7.dist-info/LICENSE
lita-0.0.7.dist-info/METADATA
lita-0.0.7.dist-info/WHEEL
lita-0.0.7.dist-info/top_level.txt
lita-0.0.7.dist-info/RECORD
