Metadata-Version: 2.2
Name: lita
Version: 0.0.7
Summary: LLM Integrated Testing & Analysis
Author-email: "seokhun.jeon" <seokhun.jeon@keti.re.kr>
License: MIT
Project-URL: Homepage, https://github.com/devcow85/lita
Classifier: Development Status :: 4 - Beta
Classifier: Programming Language :: Python :: 3.10
Classifier: Operating System :: OS Independent
Classifier: Intended Audience :: Developers
Classifier: Topic :: Scientific/Engineering :: Artificial Intelligence
Classifier: Topic :: Software Development :: Testing
Requires-Python: >=3.10
License-File: LICENSE
Requires-Dist: numpy
Requires-Dist: vllm>=0.7.2
Requires-Dist: optimum
Requires-Dist: transformers
Requires-Dist: matplotlib
Requires-Dist: onnx
Requires-Dist: onnxruntime-gpu==1.19
Requires-Dist: pandas
Requires-Dist: accelerate
